odoo8_addon_l10n_fr_siret-8.0.1.2.0.99.dev18-py2.7-nspkg.pth
odoo8_addon_l10n_fr_siret-8.0.1.2.0.99.dev18.dist-info/METADATA
odoo8_addon_l10n_fr_siret-8.0.1.2.0.99.dev18.dist-info/RECORD
odoo8_addon_l10n_fr_siret-8.0.1.2.0.99.dev18.dist-info/WHEEL
odoo8_addon_l10n_fr_siret-8.0.1.2.0.99.dev18.dist-info/namespace_packages.txt
odoo8_addon_l10n_fr_siret-8.0.1.2.0.99.dev18.dist-info/top_level.txt
odoo_addons/l10n_fr_siret/README.rst
odoo_addons/l10n_fr_siret/__init__.py
odoo_addons/l10n_fr_siret/__openerp__.py
odoo_addons/l10n_fr_siret/company.py
odoo_addons/l10n_fr_siret/company_view.xml
odoo_addons/l10n_fr_siret/partner.py
odoo_addons/l10n_fr_siret/partner_demo.xml
odoo_addons/l10n_fr_siret/partner_view.xml
odoo_addons/l10n_fr_siret/i18n/ab.po
odoo_addons/l10n_fr_siret/i18n/am.po
odoo_addons/l10n_fr_siret/i18n/ar.po
odoo_addons/l10n_fr_siret/i18n/bg.po
odoo_addons/l10n_fr_siret/i18n/bs.po
odoo_addons/l10n_fr_siret/i18n/ca.po
odoo_addons/l10n_fr_siret/i18n/cs.po
odoo_addons/l10n_fr_siret/i18n/da.po
odoo_addons/l10n_fr_siret/i18n/de.po
odoo_addons/l10n_fr_siret/i18n/el_GR.po
odoo_addons/l10n_fr_siret/i18n/en_GB.po
odoo_addons/l10n_fr_siret/i18n/es.po
odoo_addons/l10n_fr_siret/i18n/es_CR.po
odoo_addons/l10n_fr_siret/i18n/es_EC.po
odoo_addons/l10n_fr_siret/i18n/es_ES.po
odoo_addons/l10n_fr_siret/i18n/es_MX.po
odoo_addons/l10n_fr_siret/i18n/es_VE.po
odoo_addons/l10n_fr_siret/i18n/et.po
odoo_addons/l10n_fr_siret/i18n/eu.po
odoo_addons/l10n_fr_siret/i18n/fi.po
odoo_addons/l10n_fr_siret/i18n/fr.po
odoo_addons/l10n_fr_siret/i18n/fr_CA.po
odoo_addons/l10n_fr_siret/i18n/fr_CH.po
odoo_addons/l10n_fr_siret/i18n/fr_FR.po
odoo_addons/l10n_fr_siret/i18n/gl.po
odoo_addons/l10n_fr_siret/i18n/hr.po
odoo_addons/l10n_fr_siret/i18n/hr_HR.po
odoo_addons/l10n_fr_siret/i18n/hu.po
odoo_addons/l10n_fr_siret/i18n/id.po
odoo_addons/l10n_fr_siret/i18n/it.po
odoo_addons/l10n_fr_siret/i18n/ja.po
odoo_addons/l10n_fr_siret/i18n/l10n_fr_siret.pot
odoo_addons/l10n_fr_siret/i18n/lt.po
odoo_addons/l10n_fr_siret/i18n/lv.po
odoo_addons/l10n_fr_siret/i18n/mk.po
odoo_addons/l10n_fr_siret/i18n/mn.po
odoo_addons/l10n_fr_siret/i18n/nb.po
odoo_addons/l10n_fr_siret/i18n/nb_NO.po
odoo_addons/l10n_fr_siret/i18n/nl.po
odoo_addons/l10n_fr_siret/i18n/nl_BE.po
